[
  {
    "year": 2005,
    "co": 513
  },
  {
    "year": 2006,
    "co": 542
  },
  {
    "year": 2007,
    "co": 516
  },
  {
    "year": 2008,
    "co": 548
  },
  {
    "year": 2009,
    "co": 651
  },
  {
    "year": 2010,
    "co": 611
  },
  {
    "year": 2011,
    "co": 698
  },
  {
    "year": 2012,
    "co": 670
  },
  {
    "year": 2013,
    "co": 819
  },
  {
    "year": 2014,
    "co": 742
  },
  {
    "year": 2015,
    "co": 776
  },
  {
    "year": 2016,
    "co": 750
  },
  {
    "year": 2017,
    "co": 881
  },
  {
    "year": 2018,
    "co": 817
  },
  {
    "year": 2019,
    "co": 924
  },
  {
    "year": 2020,
    "co": 837
  },
  {
    "year": 2021,
    "co": 808
  },
  {
    "year": 2022,
    "co": 740
  },
  {
    "year": 2023,
    "co": 701
  },
  {
    "year": 2024,
    "co": 584
  },
  {
    "year": 2025,
    "co": 793
  }
]